learnByHear/__init__.py
learnByHear/maker.py
learnByHear/utils.py
learnByHear-0.3.dist-info/LICENSE
learnByHear-0.3.dist-info/METADATA
learnByHear-0.3.dist-info/WHEEL
learnByHear-0.3.dist-info/entry_points.txt
learnByHear-0.3.dist-info/top_level.txt
learnByHear-0.3.dist-info/RECORD
