Metadata-Version: 2.1
Name: learnByHear
Version: 0.3
Summary: Learn a new language by hearing it
Author: Rohit D
Project-URL: Homepage, https://gitlab.com/drohi/learnbyhear
Classifier: Development Status :: 3 - Alpha
Classifier: Intended Audience :: Education
Classifier: Programming Language :: Python :: 3
Classifier: License :: OSI Approved :: GNU General Public License v3 (GPLv3)
Classifier: Operating System :: POSIX :: Linux
Requires-Python: <=3.10.12,>=3.8
License-File: LICENSE
